README.md
setup.py
Multiple_dummies/Multiple_dummies.py
Multiple_dummies/__init__.py
Multiple_dummies/python_code.py
Multiple_dummies.egg-info/PKG-INFO
Multiple_dummies.egg-info/SOURCES.txt
Multiple_dummies.egg-info/dependency_links.txt
Multiple_dummies.egg-info/not-zip-safe
Multiple_dummies.egg-info/top_level.txt