Metadata-Version: 1.0
Name: Multiple-dummies
Version: 2.0
Summary: 
